xwhy/__init__.py
xwhy/datasets.py
xwhy/smile_graph.py
xwhy/smile_image.py
xwhy/smile_quantum.py
xwhy/smile_tabular.py
xwhy/smile_text.py
xwhy-0.0.0.1.dist-info/LICENSE
xwhy-0.0.0.1.dist-info/METADATA
xwhy-0.0.0.1.dist-info/WHEEL
xwhy-0.0.0.1.dist-info/top_level.txt
xwhy-0.0.0.1.dist-info/RECORD
