Metadata-Version: 2.1
Name: xwhy
Version: 0.0.0.1
Summary: Explain Why (XWhy) with Statistical Model-agnostic Interpretability with Local Explanations (SMILE)
Home-page: https://github.com/Dependable-Intelligent-Systems-Lab/xwhy
Author: Mojgan Hashemian, Koorosh Aslansefat (corresponding), Mohammad Naveed Akram, Ioannis Sorokos, Martin Walker, Yiannis Papadopoulos
Author-email: koo.ec2008@gmail.com
License: BSD
Platform: UNKNOWN
Requires-Python: >=3.5
Requires-Dist: matplotlib
Requires-Dist: numpy
Requires-Dist: scipy
Requires-Dist: tqdm (>=4.29.1)
Requires-Dist: scikit-learn (>=0.18)
Requires-Dist: scikit-image (>=0.12)
Requires-Dist: pyDOE2 (==1.3.0)
Requires-Dist: twine (==1.13.0)
Provides-Extra: dev
Requires-Dist: pytest ; extra == 'dev'
Requires-Dist: flake8 ; extra == 'dev'
